middlefield_echo/__init__.py
middlefield_echo/_impl.py
middlefield_echo/_version.py
middlefield_echo-18.1.0.dist-info/DESCRIPTION.rst
middlefield_echo-18.1.0.dist-info/METADATA
middlefield_echo-18.1.0.dist-info/RECORD
middlefield_echo-18.1.0.dist-info/WHEEL
middlefield_echo-18.1.0.dist-info/entry_points.txt
middlefield_echo-18.1.0.dist-info/metadata.json
middlefield_echo-18.1.0.dist-info/top_level.txt
