Metadata-Version: 2.0
Name: middlefield-echo
Version: 18.1.0
Summary: Middlefield Echo: Print arguments (a middlefield demonstation)
Home-page: UNKNOWN
Author: Moshe Zadka
Author-email: zadka.moshe@gmail.com
License: MIT
Platform: UNKNOWN
Requires-Dist: middlefield
